mod1/__init__.py
mod1/add.py
mod1/mult.py
mod1/sub.py
stitchstream_python-5.0.9.dist-info/METADATA
stitchstream_python-5.0.9.dist-info/WHEEL
stitchstream_python-5.0.9.dist-info/top_level.txt
stitchstream_python-5.0.9.dist-info/RECORD
