Metadata-Version: 2.1
Name: stitchstream-python
Version: 5.0.9
Summary: A sample Python project, do not download it!
Author: MC checker
Author-email: zhuzhuzhuzai@gmail.com
License: MIT
Requires-Dist: requests
